README.md
setup.cfg
setup.py
counterpointal/__init__.py
counterpointal.egg-info/PKG-INFO
counterpointal.egg-info/SOURCES.txt
counterpointal.egg-info/dependency_links.txt
counterpointal.egg-info/requires.txt
counterpointal.egg-info/top_level.txt