Metadata-Version: 2.1
Name: counterpointal
Version: 0.0.0
Summary: Tools for computer-aided composition of counterpointal music.
Home-page: UNKNOWN
Author: Nikolay Lysenko
Author-email: nikolay-lysenco@yandex.ru
License: MIT
Keywords: ai_music,algorithmic_composition,counterpoint,generative_art
Platform: UNKNOWN
Classifier: Development Status :: 1 - Planning
Classifier: Intended Audience :: Developers
Classifier: Topic :: Artistic Software
Classifier: Topic :: Scientific/Engineering :: Artificial Intelligence
Classifier: License :: OSI Approved :: MIT License
Classifier: Programming Language :: Python :: 3
Requires-Python: >=3.6
